{
  "color_matches": {
    "Белый": ["Черный", "Синий", "Красный", "Зеленый"],
    "Черный": ["Белый", "Серый", "Красный", "Синий"],
    "Синий": ["Белый", "Серый", "Бежевый"],
    "Бежевый": ["Синий", "Коричневый", "Белый"]
  },
  "occasions": {
    "Свадьба": "Рекомендуется: Костюм или формальное платье. Избегайте чисто белого.",
    "Работа": "Рекомендуется: Рубашка, брюки или юбка карандаш. Деловой стиль.",
    "Прогулка": "Рекомендуется: Футболка, джинсы и удобная обувь. Casual."
  },
  "keywords": {
    "Formal": ["свадьба", "бизнес", "встреча", "офис", "работа", "официальный"],
    "Casual": ["прогулка", "парк", "друзья", "кино", "свидание", "кафе"],
    "Sport": ["спортзал", "бег", "тренировка", "фитнес"]
  }
}